imspy/__init__.py
imspy/algorithm/__init__.py
imspy/algorithm/ccs/__init__.py
imspy/algorithm/ccs/model_std.py
imspy/algorithm/ccs/predictors.py
imspy/algorithm/ccs/utility.py
imspy/algorithm/hashing.py
imspy/algorithm/intensity/__init__.py
imspy/algorithm/intensity/predictors.py
imspy/algorithm/intensity/utility.py
imspy/algorithm/ionization/__init__.py
imspy/algorithm/ionization/predictors.py
imspy/algorithm/koina_models/__init__.py
imspy/algorithm/koina_models/access_models.py
imspy/algorithm/koina_models/input_filters.py
imspy/algorithm/mixture.py
imspy/algorithm/pretrained/__init__.py
imspy/algorithm/pretrained/ccs/ionmob-24-05-2024.keras
imspy/algorithm/pretrained/ccs/ionmob-std-20-01-2025.keras
imspy/algorithm/pretrained/charge/chargepred-26-05-2024.keras
imspy/algorithm/pretrained/intensity/Prosit2023TimsTOFPredictor/saved_model.pb
imspy/algorithm/pretrained/intensity/Prosit2023TimsTOFPredictor/variables/variables.data-00000-of-00001
imspy/algorithm/pretrained/intensity/Prosit2023TimsTOFPredictor/variables/variables.index
imspy/algorithm/pretrained/rt/rtpred-26-05-2024.keras
imspy/algorithm/pretrained/tokenizer-ptm.json
imspy/algorithm/pretrained/unimod-vocab.json
imspy/algorithm/rescoring.py
imspy/algorithm/rt/__init__.py
imspy/algorithm/rt/predictors.py
imspy/algorithm/utilities/hf_tokenizers.py
imspy/algorithm/utilities/tokenizers.py
imspy/algorithm/utility.py
imspy/chemistry/__init__.py
imspy/chemistry/amino_acids.py
imspy/chemistry/constants.py
imspy/chemistry/elements.py
imspy/chemistry/mobility.py
imspy/chemistry/sum_formula.py
imspy/chemistry/unimod.py
imspy/chemistry/utility.py
imspy/data/__init__.py
imspy/data/peptide.py
imspy/data/spectrum.py
imspy/simulation/__init__.py
imspy/simulation/acquisition.py
imspy/simulation/annotation.py
imspy/simulation/experiment.py
imspy/simulation/feature.py
imspy/simulation/handle.py
imspy/simulation/isotopes.py
imspy/simulation/noise.py
imspy/simulation/proteome.py
imspy/simulation/resources/.DS_Store
imspy-0.3.23.dist-info/METADATA
imspy-0.3.23.dist-info/WHEEL
imspy-0.3.23.dist-info/entry_points.txt
imspy-0.3.23.dist-info/RECORD
