Metadata-Version: 2.3
Name: imspy
Version: 0.3.23
Summary: A Python package for analyzing timsTOF ion mobility spectrometry data, including tools for raw data acccess and simulation.
Author: theGreatHerrLebert
Author-email: davidteschner@googlemail.com
Requires-Python: >=3.11,<3.13
Classifier: Programming Language :: Python :: 3
Classifier: Programming Language :: Python :: 3.11
Classifier: Programming Language :: Python :: 3.12
Requires-Dist: dlomix (>=0.0.6)
Requires-Dist: imspy-connector (>=0.3.23)
Requires-Dist: koinapy (>=0.0.10)
Requires-Dist: mendeleev (>=0.7.0)
Requires-Dist: mokapot (>=0.10.0)
Requires-Dist: numba (>=0.53)
Requires-Dist: numpy (>=1.21)
Requires-Dist: pandas (>=2.1)
Requires-Dist: poetry (>=2.0.0,<3.0.0)
Requires-Dist: pyarrow (>=13.0)
Requires-Dist: pyqt5 (>=5.15.11)
Requires-Dist: qdarkstyle (>=3.2.3)
Requires-Dist: sagepy (>=0.3.12)
Requires-Dist: scipy (>=1.7.1)
Requires-Dist: tabulate (>=0.9.0)
Requires-Dist: tensorflow (==2.15.*)
Requires-Dist: tensorflow-probability (>=0.22.1)
Requires-Dist: toml (>=0.10.2)
Requires-Dist: tqdm (>=4.66)
Requires-Dist: vtk (>=9.5.0)
Requires-Dist: wandb (>=0.12.1)
Requires-Dist: zstd (>=1.5.6.1)
